EQDBLinks/DBMySQL.py
EQDBLinks/DBRedist.py
EQDBLinks/DBSqlLite.py
EQDBLinks/DDLMKey.py
EQDBLinks/GetFromDB.py
EQDBLinks/__init__.py
EQSpiders/QiXianData.py
EQSpiders/__init__.py
EQStrategy/CL_HaiGuiBS.py
EQStrategy/__init__.py
EQStructure/MacdSKDJ.py
EQStructure/__init__.py
Functions/DirsFile.py
Functions/Formulae.py
Functions/LOG.py
Functions/PltImg.py
Functions/Structure.py
Functions/__init__.py
MainBase/MainBase.py
MainBase/__init__.py
THSFuncs/THSFuncs.py
THSFuncs/__init__.py
liwancai_pyscripts-0.1.0.dist-info/METADATA
liwancai_pyscripts-0.1.0.dist-info/WHEEL
liwancai_pyscripts-0.1.0.dist-info/top_level.txt
liwancai_pyscripts-0.1.0.dist-info/RECORD
