Metadata-Version: 2.4
Name: liwancai-pyscripts
Version: 0.1.0
Summary: 个人使用习惯工具Python库
Home-page: 
Author: liwancai
Author-email: 
Keywords: finance,analysis,strategy,database
Classifier: Development Status :: 3 - Alpha
Classifier: Intended Audience :: Financial and Insurance Industry
Classifier: Programming Language :: Python :: 3
Classifier: Programming Language :: Python :: 3.6
Classifier: Programming Language :: Python :: 3.7
Classifier: Programming Language :: Python :: 3.8
Classifier: Programming Language :: Python :: 3.9
Classifier: Programming Language :: Python :: 3.10
Classifier: Programming Language :: Python :: 3.11
Requires-Python: >=3.6
Requires-Dist: numpy>=1.19.0
Requires-Dist: pandas>=1.0.0
Requires-Dist: requests>=2.25.0
Requires-Dist: matplotlib>=3.3.0
Dynamic: author
Dynamic: classifier
Dynamic: description
Dynamic: description-content-type
Dynamic: keywords
Dynamic: requires-dist
Dynamic: requires-python
Dynamic: summary
